sftpgo_client/__init__.py
sftpgo_client/api_client.py
sftpgo_client/configuration.py
sftpgo_client/rest.py
sftpgo_client/api/__init__.py
sftpgo_client/api/admins_api.py
sftpgo_client/api/connections_api.py
sftpgo_client/api/defender_api.py
sftpgo_client/api/folders_api.py
sftpgo_client/api/healthcheck_api.py
sftpgo_client/api/maintenance_api.py
sftpgo_client/api/quota_api.py
sftpgo_client/api/token_api.py
sftpgo_client/api/users_api.py
sftpgo_client/models/__init__.py
sftpgo_client/models/admin.py
sftpgo_client/models/admin_filters.py
sftpgo_client/models/admin_permissions.py
sftpgo_client/models/api_response.py
sftpgo_client/models/azure_blob_fs_config.py
sftpgo_client/models/backup_data.py
sftpgo_client/models/ban_status.py
sftpgo_client/models/base_virtual_folder.py
sftpgo_client/models/connection_status.py
sftpgo_client/models/crypt_fs_config.py
sftpgo_client/models/data_provider_status.py
sftpgo_client/models/defender_unban_body.py
sftpgo_client/models/dir_permissions.py
sftpgo_client/models/extensions_filter.py
sftpgo_client/models/filesystem_config.py
sftpgo_client/models/folder_quota_scan.py
sftpgo_client/models/ftp_passive_port_range.py
sftpgo_client/models/ftp_service_status.py
sftpgo_client/models/ftpd_binding.py
sftpgo_client/models/gcs_config.py
sftpgo_client/models/inline_response200.py
sftpgo_client/models/login_methods.py
sftpgo_client/models/one_ofinline_response200.py
sftpgo_client/models/patterns_filter.py
sftpgo_client/models/permission.py
sftpgo_client/models/pwd_change.py
sftpgo_client/models/quota_scan.py
sftpgo_client/models/s3_config.py
sftpgo_client/models/score_status.py
sftpgo_client/models/secret.py
sftpgo_client/models/services_status.py
sftpgo_client/models/services_status_defender.py
sftpgo_client/models/sftp_fs_config.py
sftpgo_client/models/ssh_binding.py
sftpgo_client/models/ssh_host_key.py
sftpgo_client/models/ssh_service_status.py
sftpgo_client/models/supported_protocols.py
sftpgo_client/models/token.py
ant_sftpgo_client-1.0.1.dist-info/METADATA
ant_sftpgo_client-1.0.1.dist-info/WHEEL
ant_sftpgo_client-1.0.1.dist-info/top_level.txt
ant_sftpgo_client-1.0.1.dist-info/RECORD
